setup.py
dependencyTree/__init__.py
dependencyTree/dependencyTree.py
dependencyTree.egg-info/PKG-INFO
dependencyTree.egg-info/SOURCES.txt
dependencyTree.egg-info/dependency_links.txt
dependencyTree.egg-info/entry_points.txt
dependencyTree.egg-info/requires.txt
dependencyTree.egg-info/top_level.txt