Metadata-Version: 1.0
Name: dependencyTree
Version: 0.0.2
Summary: Analyze dependencies between components
Home-page: https://github.com/piaoying/dependencyTree
Author: handa
Author-email: 794363716@qq.com
License: MIT Licence
Keywords: pip,dependency,tree,podspec
Platform: any
